link_extractor/__init__.py
link_extractor/blogspot.py
link_extractor/config.yaml
link_extractor/domain.py
link_extractor/douban.py
link_extractor/douban_notes.py
link_extractor/get_soup.py
link_extractor/matters.py
link_extractor/name.py
link_extractor/ted.py
link_extractor/util.py
link_extractor/vocus.py
link_extractor/youtube.py
link_extractor-0.0.140.dist-info/LICENSE
link_extractor-0.0.140.dist-info/METADATA
link_extractor-0.0.140.dist-info/WHEEL
link_extractor-0.0.140.dist-info/top_level.txt
link_extractor-0.0.140.dist-info/RECORD
