Metadata-Version: 2.1
Name: link-extractor
Version: 0.0.140
Summary: Extract Links from news source, ranked by importance.
Home-page: https://github.com/gaoyunzhi/link_extractor
Author: Yunzhi Gao
Author-email: gaoyunzhi@gmail.com
License: UNKNOWN
Platform: UNKNOWN
Classifier: Programming Language :: Python :: 3
Classifier: License :: OSI Approved :: MIT License
Classifier: Operating System :: OS Independent
Requires-Python: >=3.0
License-File: LICENSE
Requires-Dist: bs4
Requires-Dist: telegram-util
Requires-Dist: cached-url
Requires-Dist: pyyaml
